dirac_webapp_packaging/__init__.py
dirac_webapp_packaging-1.0.1.dist-info/LICENSE
dirac_webapp_packaging-1.0.1.dist-info/METADATA
dirac_webapp_packaging-1.0.1.dist-info/WHEEL
dirac_webapp_packaging-1.0.1.dist-info/top_level.txt
dirac_webapp_packaging-1.0.1.dist-info/RECORD
