Metadata-Version: 2.1
Name: dirac-webapp-packaging
Version: 1.0.1
Summary: Build system for compiling javascript sources for DIRAC WebApps
Home-page: https://github.com/DIRACGrid/dirac-webapp-packaging/
License: GPL-3.0-only
Platform: UNKNOWN
Classifier: Development Status :: 5 - Production/Stable
Classifier: Intended Audience :: Science/Research
Classifier: License :: OSI Approved :: GNU General Public License v3 (GPLv3)
Classifier: Programming Language :: Python :: 3
Classifier: Environment :: Web Environment
Classifier: Topic :: Scientific/Engineering
Classifier: Topic :: Software Development :: Build Tools
Classifier: Topic :: System :: Distributed Computing
Requires-Python: >=3.9
License-File: LICENSE
Requires-Dist: setuptools (>=42)
Requires-Dist: wheel
